xdatasets/__init__.py
xdatasets/core.py
xdatasets/scripting.py
xdatasets/spatial.py
xdatasets/temporal.py
xdatasets/tutorial.py
xdatasets/utils.py
xdatasets/validations.py
xdatasets/workflows.py
xdatasets-0.3.8.dist-info/licenses/LICENSE
xdatasets-0.3.8.dist-info/WHEEL
xdatasets-0.3.8.dist-info/METADATA
xdatasets-0.3.8.dist-info/RECORD
