Metadata-Version: 2.4
Name: xdatasets
Version: 0.3.8
Summary: Easy access to Earth observation datasets with xarray.
Keywords: xdatasets,hydrology,meteorology,climate,climatology,netcdf,gridded analysis
Author-email: Sebastien Langlois <sebastien.langlois62@gmail.com>
Maintainer-email: Trevor James Smith <smith.trevorj@ouranos.ca>
Requires-Python: >=3.10.0
Classifier: Development Status :: 3 - Alpha
Classifier: Intended Audience :: Developers
Classifier: Intended Audience :: Science/Research
Classifier: License :: OSI Approved :: MIT License
Classifier: Natural Language :: English
Classifier: Operating System :: OS Independent
Classifier: Programming Language :: Python :: 3
Classifier: Programming Language :: Python :: 3.9
Classifier: Programming Language :: Python :: 3.10
Classifier: Programming Language :: Python :: 3.11
Classifier: Programming Language :: Python :: 3.12
Classifier: Topic :: Scientific/Engineering :: Hydrology
Classifier: Programming Language :: Python :: Implementation :: CPython
License-File: LICENSE
Requires-Dist: bottleneck >=1.3.1
Requires-Dist: cf-xarray >=0.6.1
Requires-Dist: cftime >=1.4.1
Requires-Dist: clisops >=0.9.2
Requires-Dist: dask[array] >=2.6
Requires-Dist: dask-geopandas >=0.4.1
Requires-Dist: geopandas >=1.0
Requires-Dist: intake
Requires-Dist: intake-geopandas
Requires-Dist: intake-xarray >=0.6.1,<2.0.0
Requires-Dist: ipython >=8.5.0
Requires-Dist: jsonpickle
Requires-Dist: numpy >=1.23
Requires-Dist: pandas >=1.5
Requires-Dist: setuptools
Requires-Dist: s3fs
Requires-Dist: scipy >=1.9.0
Requires-Dist: tqdm
Requires-Dist: xarray >=2023.1
Requires-Dist: wheel
Requires-Dist: zarr >=2.11.1
Requires-Dist: xdatasets[dev] ; extra == "all"
Requires-Dist: xdatasets[docs] ; extra == "all"
Requires-Dist: xdatasets[extra] ; extra == "all"
Requires-Dist: pip >=25.0 ; extra == "dev"
Requires-Dist: bump-my-version >=0.30.1 ; extra == "dev"
Requires-Dist: black ==25.1.0 ; extra == "dev"
Requires-Dist: blackdoc ==0.3.9 ; extra == "dev"
Requires-Dist: coverage >=7.5.0 ; extra == "dev"
Requires-Dist: flake8 >=7.1.1 ; extra == "dev"
Requires-Dist: flake8-rst-docstrings >=0.3.0 ; extra == "dev"
Requires-Dist: flit >=3.10.1,<4.0 ; extra == "dev"
Requires-Dist: isort ==6.0.1 ; extra == "dev"
Requires-Dist: mypy >=1.14.1 ; extra == "dev"
Requires-Dist: nbval ; extra == "dev"
Requires-Dist: numpydoc >=1.8.0 ; extra == "dev"
Requires-Dist: pre-commit >=3.5.0 ; extra == "dev"
Requires-Dist: pylint ; extra == "dev"
Requires-Dist: pytest >=8.3.2 ; extra == "dev"
Requires-Dist: pytest-cov >=5.0.0 ; extra == "dev"
Requires-Dist: ruff >=0.9.0 ; extra == "dev"
Requires-Dist: tokenize-rt >=3.2.0 ; extra == "dev"
Requires-Dist: tox >=4.24.1 ; extra == "dev"
Requires-Dist: watchdog >=4.0.0 ; extra == "dev"
Requires-Dist: xdoctest ; extra == "dev"
Requires-Dist: cartopy >=0.23 ; extra == "docs"
Requires-Dist: distributed >=2.0 ; extra == "docs"
Requires-Dist: furo >=2024.8.6 ; extra == "docs"
Requires-Dist: geoviews ; extra == "docs"
Requires-Dist: hvplot ; extra == "docs"
Requires-Dist: ipykernel ; extra == "docs"
Requires-Dist: jupyter_client ; extra == "docs"
Requires-Dist: matplotlib >=3.5.0 ; extra == "docs"
Requires-Dist: nbconvert <7.14 ; extra == "docs"
Requires-Dist: nbsphinx >=0.9.5 ; extra == "docs"
Requires-Dist: nc-time-axis ; extra == "docs"
Requires-Dist: netCDF4 ; extra == "docs"
Requires-Dist: panel ; extra == "docs"
Requires-Dist: pooch ; extra == "docs"
Requires-Dist: sphinx >=7.1.0 ; extra == "docs"
Requires-Dist: sphinx-codeautolink >=0.16.2 ; extra == "docs"
Requires-Dist: sphinx-copybutton >=0.5.2 ; extra == "docs"
Requires-Dist: sphinx-intl >=0.2.2 ; extra == "docs"
Requires-Dist: sphinxcontrib-confluencebuilder ; extra == "docs"
Requires-Dist: xagg ; extra == "extra"
Project-URL: Changelog, https://xdatasets.readthedocs.io/en/stable/changelog.html
Project-URL: Homepage, https://xdatasets.readthedocs.io/
Project-URL: Issue tracker, https://github.com/hydrologie/xdatasets/issues
Project-URL: Source, https://github.com/hydrologie/xdatasets
Provides-Extra: all
Provides-Extra: dev
Provides-Extra: docs
Provides-Extra: extra
